fameio/__init__.py
fameio/cli/__init__.py
fameio/cli/convert_results.py
fameio/cli/make_config.py
fameio/cli/options.py
fameio/cli/parser.py
fameio/cli/reformat.py
fameio/input/__init__.py
fameio/input/loader/__init__.py
fameio/input/loader/controller.py
fameio/input/loader/loader.py
fameio/input/metadata.py
fameio/input/resolver.py
fameio/input/scenario/__init__.py
fameio/input/scenario/agent.py
fameio/input/scenario/attribute.py
fameio/input/scenario/contract.py
fameio/input/scenario/exception.py
fameio/input/scenario/fameiofactory.py
fameio/input/scenario/generalproperties.py
fameio/input/scenario/scenario.py
fameio/input/scenario/stringset.py
fameio/input/schema/__init__.py
fameio/input/schema/agenttype.py
fameio/input/schema/attribute.py
fameio/input/schema/java_packages.py
fameio/input/schema/schema.py
fameio/input/validator.py
fameio/input/writer.py
fameio/logs.py
fameio/output/__init__.py
fameio/output/agent_type.py
fameio/output/conversion.py
fameio/output/csv_writer.py
fameio/output/data_transformer.py
fameio/output/execution_dao.py
fameio/output/files.py
fameio/output/input_dao.py
fameio/output/metadata/__init__.py
fameio/output/metadata/compiler.py
fameio/output/metadata/json_writer.py
fameio/output/metadata/locator.py
fameio/output/metadata/oeo_template.py
fameio/output/metadata/template_reader.py
fameio/output/output_dao.py
fameio/output/reader.py
fameio/output/yaml_writer.py
fameio/scripts/__init__.py
fameio/scripts/convert_results.py
fameio/scripts/exception.py
fameio/scripts/make_config.py
fameio/scripts/reformat.py
fameio/scripts/REUSE.toml
fameio/series.py
fameio/time.py
fameio/tools.py
fameio-3.5.3.dist-info/entry_points.txt
fameio-3.5.3.dist-info/LICENSE.txt
fameio-3.5.3.dist-info/LICENSES/Apache-2.0.txt
fameio-3.5.3.dist-info/LICENSES/CC-BY-4.0.txt
fameio-3.5.3.dist-info/LICENSES/CC-BY-ND-4.0.txt
fameio-3.5.3.dist-info/LICENSES/CC0-1.0.txt
fameio-3.5.3.dist-info/METADATA
fameio-3.5.3.dist-info/WHEEL
fameio-3.5.3.dist-info/RECORD
