Metadata-Version: 2.3
Name: fameio
Version: 3.5.3
Summary: Tools for input preparation and output digestion of FAME models
License: Apache-2.0
Keywords: FAME,fameio,agent-based modelling,energy systems
Author: Felix Nitsch
Author-email: fame@dlr.de
Maintainer: Felix Nitsch
Maintainer-email: fame@dlr.de
Requires-Python: >=3.9,<4.0
Classifier: Development Status :: 5 - Production/Stable
Classifier: Environment :: Console
Classifier: Intended Audience :: Science/Research
Classifier: License :: OSI Approved :: Apache Software License
Classifier: Operating System :: OS Independent
Classifier: Programming Language :: Python :: 3
Classifier: Programming Language :: Python :: 3.9
Classifier: Programming Language :: Python :: 3.10
Classifier: Programming Language :: Python :: 3.11
Classifier: Programming Language :: Python :: 3.12
Classifier: Programming Language :: Python :: 3.13
Classifier: Topic :: Scientific/Engineering
Requires-Dist: fameprotobuf (>=2.1.0,<3.0)
Requires-Dist: pandas (>=1.0,<3.0)
Requires-Dist: pyyaml (>=6.0,<7.0)
Project-URL: Changelog, https://gitlab.com/fame-framework/fame-io/-/blob/main/CHANGELOG.md
Project-URL: Homepage, https://helmholtz.software/software/fame
Project-URL: Issue Tracking, https://gitlab.com/fame-framework/fame-io/-/issues
Project-URL: Repository, https://gitlab.com/fame-framework/fame-io
